minfo/__init__.py
minfo/mi_bool.py
minfo/mi_c.cpython-310-darwin.so
minfo/mi_float.py
minfo-0.0.7.dist-info/LICENSE
minfo-0.0.7.dist-info/METADATA
minfo-0.0.7.dist-info/WHEEL
minfo-0.0.7.dist-info/top_level.txt
minfo-0.0.7.dist-info/RECORD
