Metadata-Version: 2.1
Name: minfo
Version: 0.0.7
Summary: Python-based mutual information estimator, designed for multiple data types.
Home-page: https://github.com/NeoNeuron/minfo
Author: Kai Chen
Author-email: Kai Chen <kchen513@sjtu.edu.cn>
License: MIT License        
Project-URL: Homepage, https://github.com/neoneuron/minfo
Project-URL: Bug Tracker, https://github.com/neoneuron/minfo/issues
Classifier: Programming Language :: Python :: 3
Classifier: License :: OSI Approved :: MIT License
Classifier: Operating System :: OS Independent
Requires-Python: >=3.7
License-File: LICENSE
Requires-Dist: numpy
Requires-Dist: cython
Requires-Dist: numba
